hksdk.py
lib/linux/HCCore.lib
lib/linux/HCNetSDK.lib
lib/linux/PlayCtrl.lib
lib/linux/HCNetSDKCom/HCAlarm.lib
lib/linux/HCNetSDKCom/HCGeneralCfgMgr.lib
lib/linux/HCNetSDKCom/HCPreview.lib
lib/win/AudioRender.dll
lib/win/HCCore.dll
lib/win/HCNetSDK.dll
lib/win/PlayCtrl.dll
lib/win/libcrypto-1_1-x64.dll
lib/win/libssl-1_1-x64.dll
lib/win/HCNetSDKCom/HCCoreDevCfg.dll
lib/win/HCNetSDKCom/HCGeneralCfgMgr.lib
lib/win/HCNetSDKCom/HCPreview.dll
lib/win/HCNetSDKCom/SystemTransform.dll
lib/win/SdkLog_Python/SdkLog_1_W.log
process/HCNetSDK.py
process/PlayCtrl.py
process/__ini__.py
process/video_control.py
process/__pycache__/HCNetSDK.cpython-310.pyc
process/__pycache__/PlayCtrl.cpython-310.pyc
process/__pycache__/video_control.cpython-310.pyc
hksdk-1.0.0.dist-info/METADATA
hksdk-1.0.0.dist-info/WHEEL
hksdk-1.0.0.dist-info/top_level.txt
hksdk-1.0.0.dist-info/RECORD
